tennis/__init__.py
tennis/match.py
tennis/tiebreak.py
tennis-0.1.7.dist-info/LICENSE
tennis-0.1.7.dist-info/METADATA
tennis-0.1.7.dist-info/WHEEL
tennis-0.1.7.dist-info/top_level.txt
tennis-0.1.7.dist-info/RECORD
