Metadata-Version: 2.1
Name: tennis
Version: 0.1.7
Summary: A library for tracking tennis matches and scoring
Home-page: https://github.com/bear102/tennis
Author: bear102
License: MIT
Project-URL: Homepage, https://github.com/bear102/tennis
Classifier: Programming Language :: Python :: 3
Classifier: License :: OSI Approved :: MIT License
Classifier: Operating System :: OS Independent
Requires-Python: >=3.7
License-File: LICENSE
